odoo/addons/opcions/__init__.py
odoo/addons/opcions/__manifest__.py
odoo/addons/opcions/models/__init__.py
odoo/addons/opcions/models/res_partner.py
odoo/addons/opcions/models/subscription_request.py
odoo12_addon_opcions-12.0.1.0.0.dist-info/METADATA
odoo12_addon_opcions-12.0.1.0.0.dist-info/WHEEL
odoo12_addon_opcions-12.0.1.0.0.dist-info/top_level.txt
odoo12_addon_opcions-12.0.1.0.0.dist-info/RECORD
